pyjsend/__init__.py
pyjsend/responses.py
pyjsend/tests/__init__.py
pyjsend/tests/test_json_schema.py
python_jsend_response-0.0.3.dist-info/METADATA
python_jsend_response-0.0.3.dist-info/WHEEL
python_jsend_response-0.0.3.dist-info/top_level.txt
python_jsend_response-0.0.3.dist-info/RECORD
