Metadata-Version: 2.1
Name: python-jsend-response
Version: 0.0.3
Summary: python-jsend-response is a simply python implementation of JSend.
Home-page: https://github.com/AntLouiz/pyjsend
Author: AntLouiz
Author-email: luizrodrigo46@hotmail.com
License: UNKNOWN
Platform: UNKNOWN
Classifier: Programming Language :: Python :: 3
Classifier: License :: OSI Approved :: MIT License
Classifier: Operating System :: OS Independent
Requires-Python: >=3.5
